[
  {
    "type": "atm",
    "name": "bitcoindepot",
    "category": "",
    "subcategory": "",
    "url": "https://bitcoindepot.com/",
    "size": ""    
  },
  {
    "type": "atm",
    "name": "bitstop",
    "category": "",
    "subcategory": "",
    "url": "https://bitstop.co/",
    "size": ""    
  },
  {
    "type": "atm",
    "name": "coinflip",
    "category": "",
    "subcategory": "",
    "url": "https://coinflip.tech/",
    "size": ""    
  },
  {
    "type": "atm",
    "name": "rockitcoin",
    "category": "",
    "subcategory": "",
    "url": "https://www.rockitcoin.com/",
    "size": ""    
  },
  {
    "type": "gambling",
    "name": "bitcasino",
    "category": "",
    "subcategory": "",
    "url": "https://bitcasino.io/",
    "size": ""
  },
  {
    "type": "gambling",
    "name": "bitspincasino1",
    "category": "",
    "subcategory": "",
    "url": "https://www.bitspincasino1.com/",
    "size": ""
  },
  {
    "type": "gambling",
    "name": "fairspin",
    "category": "",
    "subcategory": "",
    "url": "https://fairspin.io/",
    "size": ""
  },
  {
    "type": "mixers",
    "name": "blindmixer",
    "category": "",
    "subcategory": "",
    "url": "https://blindmixer.com/",
    "size": ""
  },
  {
    "type": "mixers",
    "name": "mixer",
    "category": "",
    "subcategory": "",
    "url": "https://mixer.money/",
    "size": ""
  },
  {
    "type": "mixers",
    "name": "mixero",
    "category": "",
    "subcategory": "",
    "url": "https://mixero.io/",
    "size": ""
  },
  {
    "type": "mixers",
    "name": "samouraiwallet",
    "category": "",
    "subcategory": "",
    "url": "https://samouraiwallet.com/",
    "size": ""
  },
  {
    "type": "mixers",
    "name": "sinbad",
    "category": "",
    "subcategory": "",
    "url": "https://sinbad.io/",
    "size": ""
  },
  {
    "type": "mixers",
    "name": "unijoin",
    "category": "",
    "subcategory": "",
    "url": "https://unijoin.io/",
    "size": ""
  },
  {
    "type": "mixers",
    "name": "yomix",
    "category": "",
    "subcategory": "",
    "url": "https://yomix.io/en",
    "size": ""
  },
  {
    "type": "mixers",
    "name": "wasabiwallet",
    "category": "",
    "subcategory": "",
    "url": "https://wasabiwallet.io/",
    "size": ""
  }
]
